AUTHORS.rst
CONTRIBUTING.rst
HISTORY.rst
LICENSE
MANIFEST.in
README.rst
setup.py
django_httplog.egg-info/PKG-INFO
django_httplog.egg-info/SOURCES.txt
django_httplog.egg-info/dependency_links.txt
django_httplog.egg-info/not-zip-safe
django_httplog.egg-info/top_level.txt
httplog/__init__.py
httplog/admin.py
httplog/middleware.py
httplog/models.py
httplog/utils.py
httplog/migrations/0001_initial.py
httplog/migrations/__init__.py