Metadata-Version: 1.1
Name: django-httplog
Version: 0.2.3
Summary: Very simple http request-response log in database for debugging APIs.
Home-page: https://github.com/futurecolors/django-httplog
Author: Ilya Baryshev
Author-email: baryshev@gmail.com
License: BSD
Keywords: django-httplog
Platform: UNKNOWN
Classifier: Development Status :: 3 - Alpha
Classifier: Framework :: Django
Classifier: Intended Audience :: Developers
Classifier: License :: OSI Approved :: BSD License
Classifier: Natural Language :: English
Classifier: Programming Language :: Python :: 2
Classifier: Programming Language :: Python :: 2.6
Classifier: Programming Language :: Python :: 2.7
Classifier: Programming Language :: Python :: 3
Classifier: Programming Language :: Python :: 3.3
